COT/__init__.py
COT/_version.py
COT/data_validation.py
COT/file_reference.py
COT/utilities.py
COT/xml_file.py
COT/commands/__init__.py
COT/commands/add_disk.py
COT/commands/add_file.py
COT/commands/command.py
COT/commands/demo_logging.py
COT/commands/deploy.py
COT/commands/deploy_esxi.py
COT/commands/edit_hardware.py
COT/commands/edit_product.py
COT/commands/edit_properties.py
COT/commands/help.py
COT/commands/info.py
COT/commands/inject_config.py
COT/commands/install_helpers.py
COT/commands/remove_file.py
COT/commands/tests/__init__.py
COT/commands/tests/command_testcase.py
COT/commands/tests/test_add_disk.py
COT/commands/tests/test_add_file.py
COT/commands/tests/test_command.py
COT/commands/tests/test_deploy.py
COT/commands/tests/test_deploy_esxi.py
COT/commands/tests/test_doctests.py
COT/commands/tests/test_edit_hardware.py
COT/commands/tests/test_edit_product.py
COT/commands/tests/test_edit_properties.py
COT/commands/tests/test_info.py
COT/commands/tests/test_inject_config.py
COT/commands/tests/test_install_helpers.py
COT/commands/tests/test_remove_file.py
COT/disks/__init__.py
COT/disks/disk.py
COT/disks/iso.py
COT/disks/qcow2.py
COT/disks/raw.py
COT/disks/vmdk.py
COT/disks/tests/__init__.py
COT/disks/tests/test_disk_representation.py
COT/disks/tests/test_iso.py
COT/disks/tests/test_qcow2.py
COT/disks/tests/test_raw.py
COT/disks/tests/test_vmdk.py
COT/docs/man/cot-add-disk.1
COT/docs/man/cot-add-file.1
COT/docs/man/cot-deploy-esxi.1
COT/docs/man/cot-deploy.1
COT/docs/man/cot-edit-hardware.1
COT/docs/man/cot-edit-product.1
COT/docs/man/cot-edit-properties.1
COT/docs/man/cot-info.1
COT/docs/man/cot-inject-config.1
COT/docs/man/cot-install-helpers.1
COT/docs/man/cot-remove-file.1
COT/docs/man/cot.1
COT/helpers/__init__.py
COT/helpers/apt_get.py
COT/helpers/brew.py
COT/helpers/fatdisk.py
COT/helpers/gcc.py
COT/helpers/helper.py
COT/helpers/isoinfo.py
COT/helpers/make.py
COT/helpers/mkisofs.py
COT/helpers/ovftool.py
COT/helpers/port.py
COT/helpers/qemu_img.py
cot-2.2.1.dist-info/AUTHORS.txt
cot-2.2.1.dist-info/LICENSE.txt
cot-2.2.1.dist-info/METADATA
cot-2.2.1.dist-info/WHEEL
cot-2.2.1.dist-info/entry_points.txt
cot-2.2.1.dist-info/pbr.json
cot-2.2.1.dist-info/setup_requires.txt
cot-2.2.1.dist-info/top_level.txt
cot-2.2.1.dist-info/RECORD
