Metadata-Version: 2.1
Name: cot
Version: 2.2.1
Summary: Common OVF Tool
Home-page: https://github.com/glennmatthews/cot
Author: Glenn Matthews
Author-email: glenn@e-dad.net
License: MIT
Keywords: virtualization ovf ova esxi vmware vcenter
Platform: UNKNOWN
Classifier: Development Status :: 5 - Production/Stable
Classifier: Intended Audience :: Developers
Classifier: Intended Audience :: Information Technology
Classifier: Intended Audience :: System Administrators
Classifier: Topic :: Software Development :: Libraries :: Python Modules
Classifier: Topic :: System :: Emulators
Classifier: Topic :: System :: Installation/Setup
Classifier: Topic :: System :: Software Distribution
Classifier: Topic :: System :: Systems Administration
Classifier: License :: OSI Approved :: MIT License
Classifier: Environment :: Console
Classifier: Operating System :: MacOS :: MacOS X
Classifier: Operating System :: POSIX :: Linux
Classifier: Programming Language :: Python :: 2
Classifier: Programming Language :: Python :: 2.7
Classifier: Programming Language :: Python :: 3
Classifier: Programming Language :: Python :: 3.4
Classifier: Programming Language :: Python :: 3.5
Classifier: Programming Language :: Python :: 3.6
Classifier: Programming Language :: Python :: 3.7
Classifier: Programming Language :: Python :: Implementation :: CPython
Classifier: Programming Language :: Python :: Implementation :: PyPy
Requires-Python: >=2.7, !=3.0.*, !=3.1.*, !=3.2.*, !=3.3.*, <4
Requires-Dist: argparse
Requires-Dist: colorlog (>=2.5.0)
Requires-Dist: pyvmomi (>=5.5.0.2014.1)
Requires-Dist: requests (>=2.5.1)
Requires-Dist: verboselogs (>=1.6)
Requires-Dist: pyOpenSSL ; python_version < "2.7.9"
Requires-Dist: ndg-httpsclient ; python_version < "2.7.9"
Requires-Dist: psutil (>=5.6.7) ; python_version < "3.3"
Requires-Dist: backports.shutil-get-terminal-size ; python_version < "3.3"
Requires-Dist: enum34 ; python_version < "3.4"
Provides-Extra: tab-completion
Requires-Dist: argcomplete (>=1.3.0) ; extra == 'tab-completion'
